transfer_lmir/__init__.py
transfer_lmir/estimation.py
transfer_lmir-0.0.7.dist-info/LICENSE.txt
transfer_lmir-0.0.7.dist-info/METADATA
transfer_lmir-0.0.7.dist-info/WHEEL
transfer_lmir-0.0.7.dist-info/top_level.txt
transfer_lmir-0.0.7.dist-info/RECORD
