Metadata-Version: 2.1
Name: transfer-lmir
Version: 0.0.7
Summary: Functions to perform calibration transfer with LMIR
Author: Giverny Robert, Francis B. Lavoie, Ryan Gosselin
Author-email: giverny.robert@usherbrooke.ca, francis.b.lavoie@usherbrooke.ca, ryan.gosselin@usherbrooke.ca
Classifier: Programming Language :: Python :: 3
Classifier: License :: OSI Approved :: MIT License
Classifier: Operating System :: OS Independent
License-File: LICENSE.txt
